Metadata-Version: 1.0
Name: sftpy
Version: 1.0.5
Summary: A python SFTP module that supports mget-style filename globby patterns
Home-page: https://github.com/phenicle/sftpy
Author: Phenicle
Author-email: pheniclebeefheart@gmail.com
License: LGPLv3
Platform: UNKNOWN
